dymcpxx/__init__.py
dymcpxx/server.py
dymcpxx-1.1.0.dist-info/METADATA
dymcpxx-1.1.0.dist-info/WHEEL
dymcpxx-1.1.0.dist-info/entry_points.txt
dymcpxx-1.1.0.dist-info/licenses/LICENSE
dymcpxx-1.1.0.dist-info/RECORD
